odoo10_addon_shopinvader_guest_mode-10.0.1.1.0-py3.8-nspkg.pth
odoo/addons/shopinvader_guest_mode/README.rst
odoo/addons/shopinvader_guest_mode/__init__.py
odoo/addons/shopinvader_guest_mode/__manifest__.py
odoo/addons/shopinvader_guest_mode/data/ir_cron.xml
odoo/addons/shopinvader_guest_mode/demo/partner_demo.xml
odoo/addons/shopinvader_guest_mode/i18n/shopinvader_guest_mode.pot
odoo/addons/shopinvader_guest_mode/models/__init__.py
odoo/addons/shopinvader_guest_mode/models/shopinvader_backend.py
odoo/addons/shopinvader_guest_mode/models/shopinvader_partner.py
odoo/addons/shopinvader_guest_mode/readme/CONTRIBUTORS.rst
odoo/addons/shopinvader_guest_mode/readme/CREDITS.rst
odoo/addons/shopinvader_guest_mode/readme/DESCRIPTION.rst
odoo/addons/shopinvader_guest_mode/readme/USAGE.rst
odoo/addons/shopinvader_guest_mode/services/__init__.py
odoo/addons/shopinvader_guest_mode/services/address.py
odoo/addons/shopinvader_guest_mode/services/customer.py
odoo/addons/shopinvader_guest_mode/services/guest_service.py
odoo/addons/shopinvader_guest_mode/static/description/icon.png
odoo/addons/shopinvader_guest_mode/static/description/index.html
odoo/addons/shopinvader_guest_mode/tests/__init__.py
odoo/addons/shopinvader_guest_mode/tests/test_guest_binding.py
odoo/addons/shopinvader_guest_mode/tests/test_guest_service.py
odoo/addons/shopinvader_guest_mode/tests/test_shopinvader_backend.py
odoo/addons/shopinvader_guest_mode/tests/test_shopinvader_partner.py
odoo/addons/shopinvader_guest_mode/views/shopinvader_backend.xml
odoo/addons/shopinvader_guest_mode/views/shopinvader_partner.xml
odoo/addons/shopinvader_guest_mode/wizards/__init__.py
odoo/addons/shopinvader_guest_mode/wizards/partner_binding_line.py
odoo/addons/shopinvader_guest_mode/wizards/partner_binding_wizard.py
odoo/addons/shopinvader_guest_mode/wizards/partner_binding_wizard.xml
odoo10_addon_shopinvader_guest_mode-10.0.1.1.0.dist-info/METADATA
odoo10_addon_shopinvader_guest_mode-10.0.1.1.0.dist-info/WHEEL
odoo10_addon_shopinvader_guest_mode-10.0.1.1.0.dist-info/namespace_packages.txt
odoo10_addon_shopinvader_guest_mode-10.0.1.1.0.dist-info/top_level.txt
odoo10_addon_shopinvader_guest_mode-10.0.1.1.0.dist-info/RECORD
